surquest/utils/poscore/client.py
surquest/utils/poscore/credentials.py
surquest/utils/poscore/errors.py
surquest/utils/poscore/models/__init__.py
surquest/utils/poscore/models/campaign_row_installation.py
surquest/utils/poscore/models/installation_models.py
surquest/utils/poscore/models/blobs/__init__.py
surquest/utils/poscore/models/blobs/blob.py
surquest/utils/poscore/models/campaigns/__init__.py
surquest/utils/poscore/models/campaigns/brand.py
surquest/utils/poscore/models/campaigns/campaign.py
surquest/utils/poscore/models/campaigns/campaign_lock.py
surquest/utils/poscore/models/campaigns/campaign_response.py
surquest/utils/poscore/models/campaigns/campaign_row.py
surquest/utils/poscore/models/campaigns/campaign_status.py
surquest/utils/poscore/models/campaigns/carrier.py
surquest/utils/poscore/models/campaigns/company.py
surquest/utils/poscore/models/campaigns/component.py
surquest/utils/poscore/models/campaigns/contact.py
surquest/utils/poscore/models/campaigns/customer_reference.py
surquest/utils/poscore/models/campaigns/partner.py
surquest/utils/poscore/models/campaigns/sales_employee.py
surquest/utils/poscore/models/installations/__init__.py
surquest/utils/poscore/models/installations/campaign_row_installation.py
surquest/utils/poscore/models/installations/installation_response.py
surquest/utils/poscore/models/installations/installation_status_payload.py
surquest/utils/poscore/models/installations/location_installation.py
surquest_utils_poscore_client-0.0.4.dist-info/METADATA
surquest_utils_poscore_client-0.0.4.dist-info/WHEEL
surquest_utils_poscore_client-0.0.4.dist-info/licenses/LICENSE
surquest_utils_poscore_client-0.0.4.dist-info/RECORD
