Metadata-Version: 2.4
Name: surquest-utils-poscore-client
Version: 0.0.4
Summary: Python client for POS Media Data Core APIs with credential handling and convenience helpers.
Project-URL: Homepage, https://github.com/surquest/python-utils-data-core-client
Project-URL: Bug Tracker, https://github.com/surquest/python-utils-data-core-client/issues
Author-email: Surquest <michal.svarc@surquest.com>
License-File: LICENSE
Requires-Python: >=3.9
Requires-Dist: pydantic<3.0,>=2.10.9
Requires-Dist: requests<3.0,>=2.32.5
Provides-Extra: test
Requires-Dist: pytest-cov==7.0.0; extra == 'test'
Requires-Dist: pytest==9.0.2; extra == 'test'
